{
  "resourceType": "StructureDefinition",
  "id": "RLOrganizationAsstAfferenza",
  "url": "https://fhir.siss.regione.lombardia.it/StructureDefinition/RLOrganizationAsstAfferenza",
  "name": "RLOrganizationAsstAfferenza",
  "description": "ASST sotto la quale l'ente eroga servizi sociosanitari sul territorio di competenza",
  "status": "active",
  "experimental": false,
  "fhirVersion": "4.0.1",
  "kind": "complex-type",
  "abstract": false,
  "context": [
    {
      "type": "element",
      "expression": "Organization"
    }
  ],
  "type": "Extension",
  "baseDefinition": "http://hl7.org/fhir/StructureDefinition/Extension",
  "derivation": "constraint",
  "differential": {
    "element": [
      {
        "id": "Extension.url",
        "path": "Extension.url",
        "fixedUri": "https://fhir.siss.regione.lombardia.it/StructureDefinition/RLOrganizationAsstAfferenza"
      },
      {
        "id": "Extension.value[x]",
        "path": "Extension.value[x]",
        "type": [
          {
            "code": "CodeableConcept"
          }
        ]
      }
    ]
  }
}